seznami/__init__.py
seznami/funcs.py
seznami-0.0.2.dist-info/LICENSE
seznami-0.0.2.dist-info/METADATA
seznami-0.0.2.dist-info/WHEEL
seznami-0.0.2.dist-info/top_level.txt
seznami-0.0.2.dist-info/RECORD
