Metadata-Version: 2.1
Name: seznami
Version: 0.0.2
Summary: Seznami in stvari
Author-email: ravijol1 <liamstaric@gmail.com>
Classifier: Programming Language :: Python :: 3
Classifier: License :: OSI Approved :: MIT License
Classifier: Operating System :: OS Independent
Requires-Python: >=3.8
License-File: LICENSE
